{"cameraMode":{"drawMode":0,"name":"Shaded","section":"Shading Mode"},"sceneLighting":false,"audioPlay":false,"sceneViewState":{"m_AlwaysRefresh":false,"showFog":true,"showSkybox":false,"showFlares":true,"showImageEffects":true,"showParticleSystems":true,"showVisualEffectGraphs":true,"m_FxEnabled":true},"in2DMode":false,"pivot":{"x":6.0,"y":4.0,"z":21.0},"rotation":{"x":0.05509593337774277,"y":-0.7179387807846069,"z":0.057196807116270068,"w":0.6915651559829712},"size":22.203603744506837,"orthographic":false}